{
    "title": "Thorne's Links",
    "description": "All of Thorne's various social links in one place.",
    "header": {
        "fontFamily": "font-mono"
    },
    "buttons": {
        "fontFamily": "font-mono",
        "bgColor": "bg-slate-800",
        "hoverColor": "hover:bg-slate-700",
        "textColor": "text-orange"
    },
    "links": [
        {
            "name": "website",
            "url": "https://www.ens0.me",
            "icon": "home"
        },
        {
            "name": "smol quest",
            "url": "https://smol.quest/u/ens0",
            "icon": "gamepad"
        },
        {
            "name": "X",
            "url": "https://x.com/existentialenso",
            "icon": "x"
        },
        {
            "name": "Bluesky",
            "url": "https://bsky.app/profile/ens0.me",
            "icon": "bluesky"
        },
        {
            "name": "GitHub",
            "url": "https://github.com/existentialenso",
            "icon": "github"
        },
        {
            "name": "Reddit",
            "url": "https://www.reddit.com/u/existentialenso",
            "icon": "reddit"
        },
        {
            "name": "LinkedIn",
            "url": "https://www.linkedin.com/in/existentialenso",
            "icon": "linkedin"
        },
        {
            "name": "Duolingo",
            "url": "https://www.duolingo.com/profile/existentialenso",
            "icon": "duolingo"
        },
        {
            "name": "Instagram",
            "url": "https://www.instagram.com/existentialenso",
            "icon": "instagram"
        }
    ]
}